tno/mpc/protocols/secure_inner_join/__init__.py
tno/mpc/protocols/secure_inner_join/database_owner.py
tno/mpc/protocols/secure_inner_join/helper.py
tno/mpc/protocols/secure_inner_join/lsh.py
tno/mpc/protocols/secure_inner_join/phonem.py
tno/mpc/protocols/secure_inner_join/player.py
tno/mpc/protocols/secure_inner_join/py.typed
tno/mpc/protocols/secure_inner_join/utils.py
tno/mpc/protocols/secure_inner_join/test/__init__.py
tno/mpc/protocols/secure_inner_join/test/conftest.py
tno/mpc/protocols/secure_inner_join/test/test_lsh.py
tno/mpc/protocols/secure_inner_join/test/test_phonem.py
tno/mpc/protocols/secure_inner_join/test/test_secure_inner_join.py
tno/mpc/protocols/secure_inner_join/test/test_secure_matching.py
tno.mpc.protocols.secure_inner_join-2.0.2.dist-info/LICENSE
tno.mpc.protocols.secure_inner_join-2.0.2.dist-info/METADATA
tno.mpc.protocols.secure_inner_join-2.0.2.dist-info/WHEEL
tno.mpc.protocols.secure_inner_join-2.0.2.dist-info/top_level.txt
tno.mpc.protocols.secure_inner_join-2.0.2.dist-info/RECORD
