Metadata-Version: 2.1
Name: tno.mpc.protocols.secure_inner_join
Version: 2.0.2
Summary: Secure inner join using Paillier homomorphic encryption and a helper party
Author-email: TNO PET Lab <petlab@tno.nl>
Maintainer-email: TNO PET Lab <petlab@tno.nl>
License: Apache License, Version 2.0
Project-URL: Homepage, https://pet.tno.nl/
Project-URL: Documentation, https://docs.pet.tno.nl/mpc/protocols/secure_inner_join/2.0.2
Project-URL: Source, https://github.com/TNO-MPC/protocols.secure_inner_join
Keywords: TNO,MPC,multi-party computation,protocols,secure inner join,matching,fuzzy,approximate matching
Platform: any
Classifier: License :: OSI Approved :: Apache Software License
Classifier: Programming Language :: Python :: 3
Classifier: Operating System :: OS Independent
Classifier: Intended Audience :: Developers
Classifier: Intended Audience :: Information Technology
Classifier: Intended Audience :: Science/Research
Classifier: Typing :: Typed
Classifier: Topic :: Security :: Cryptography
Requires-Python: >=3.8
License-File: LICENSE
Requires-Dist: bitarray
Requires-Dist: mypy_extensions
Requires-Dist: numpy<2,>=1.24.4
Requires-Dist: randomgen
Requires-Dist: tno.mpc.communication[bitarray]~=4.8
Requires-Dist: tno.mpc.encryption_schemes.paillier~=3.0
Provides-Extra: scripts
Requires-Dist: pandas; extra == "scripts"
Provides-Extra: gmpy
Requires-Dist: tno.mpc.encryption_schemes.paillier[gmpy]; extra == "gmpy"
Provides-Extra: tests
Requires-Dist: pytest>=8.1; extra == "tests"
Requires-Dist: pytest-asyncio; extra == "tests"
